inmanta_plugins/graph/__init__.py
inmanta_plugins/graph/setup.cfg
inmanta_plugins/graph/model/_init.cf
inmanta_module_graph-1.0.1.dist-info/METADATA
inmanta_module_graph-1.0.1.dist-info/WHEEL
inmanta_module_graph-1.0.1.dist-info/top_level.txt
inmanta_module_graph-1.0.1.dist-info/RECORD
