Metadata-Version: 2.1
Name: inmanta-module-graph
Version: 1.0.1
License: Apache V2
Requires-Dist: inmanta-module-std
